validators/__init__.py
validators/verificadores.py
validatorGP-0.1.dist-info/METADATA
validatorGP-0.1.dist-info/WHEEL
validatorGP-0.1.dist-info/top_level.txt
validatorGP-0.1.dist-info/RECORD
